multporn/__init__.py
multporn/multporn.py
multporn-1.4.0.dist-info/LICENSE
multporn-1.4.0.dist-info/METADATA
multporn-1.4.0.dist-info/WHEEL
multporn-1.4.0.dist-info/top_level.txt
multporn-1.4.0.dist-info/RECORD
