Metadata-Version: 2.1
Name: multporn
Version: 1.4.0
Summary: python library used to interact with multporn.net via python
Home-page: https://github.com/pyporn-san/Multporn
Author: pyporn-san
Author-email: pypornsan@gmail.com
License: GPL-3.0
Classifier: Development Status :: 2 - Pre-Alpha
Classifier: Intended Audience :: Developers
Classifier: License :: OSI Approved :: GNU General Public License v3 (GPLv3)
Classifier: License :: OSI Approved :: GNU Lesser General Public License v3 (LGPLv3)
Classifier: Natural Language :: English
Classifier: Operating System :: OS Independent
Classifier: Programming Language :: Python :: 3
Classifier: Programming Language :: Python :: 3 :: Only
Classifier: Topic :: Software Development :: Libraries
Classifier: Topic :: Utilities
Requires-Python: >=3.8
License-File: LICENSE
Requires-Dist: Faker (>=16.6.1)
Requires-Dist: beautifulsoup4 (>=4.10.0)
Requires-Dist: pathvalidate (>=2.5.0)
Requires-Dist: requests (>=2.28.2)
Requires-Dist: tqdm (>=4.61.1)
Requires-Dist: urllib3 (>=1.26.7)
